textcut/__init__.py
textcut/textcut.py
textcut/localisation/__init__.py
textcut/localisation/fr.json
textcut/localisation/lang.py
textcut/localisation/schema.json
textcut-0.0.4.dist-info/METADATA
textcut-0.0.4.dist-info/WHEEL
textcut-0.0.4.dist-info/licenses/LICENSE
textcut-0.0.4.dist-info/RECORD
