Metadata-Version: 2.1
Name: textcut
Version: 0.0.4
Summary: A context-dependent text wrapper.
Project-URL: Homepage, https://gitlab.com/ohne_sonne/text-cut
Project-URL: Bug Tracker, https://gitlab.com/ohne_sonne/text-cut/-/issues
Author-email: Zonder Zon <ohne_sonne_1312@protonmail.com>
License-File: LICENSE
Classifier: License :: Public Domain
Classifier: Operating System :: OS Independent
Classifier: Programming Language :: Python :: 3
Requires-Python: >=3.7
